{
  "label": "palestine",
  "permalink": "/docs/tags/palestine",
  "allTagsPath": "/docs/tags",
  "count": 2,
  "items": [
    {
      "id": "Food/Recipes/Maqlouba",
      "title": "Description",
      "description": "Maqlouba means upside down in Arabic. It is quite easy to work with.  Actually, quite an easy dish to make for a lot of people, I might have spent around and hour maybe 90 minutes on it.",
      "permalink": "/docs/Food/Recipes/Maqlouba"
    },
    {
      "id": "Books/Book Reviews/On Palestine",
      "title": "On Palestine",
      "description": "This book is a critique of the horrendous way Israel has treated the Palestinians. It delves into all the classical arguments on the situations and dispels them. Their main argument is that Palestinians have as much of a right to their land as the Israelis.",
      "permalink": "/docs/Books/Book Reviews/On Palestine"
    }
  ],
  "unlisted": false
}